sphinxcontrib/typer/__init__.py
sphinxcontrib_typer-0.7.2.dist-info/METADATA
sphinxcontrib_typer-0.7.2.dist-info/WHEEL
sphinxcontrib_typer-0.7.2.dist-info/licenses/LICENSE
sphinxcontrib_typer-0.7.2.dist-info/RECORD
