Metadata-Version: 2.4
Name: sphinxcontrib-typer
Version: 0.7.2
Summary: Auto generate docs for typer commands.
Project-URL: Homepage, https://sphinxcontrib-typer.readthedocs.io
Project-URL: Documentation, https://sphinxcontrib-typer.readthedocs.io
Project-URL: Repository, https://github.com/sphinx-contrib/typer
Project-URL: Issues, https://github.com/sphinx-contrib/typer/issues
Project-URL: Changelog, https://sphinxcontrib-typer.readthedocs.io/en/stable/changelog.html
Author-email: Brian Kohan <bckohan@gmail.com>
License-Expression: MIT
License-File: LICENSE
Classifier: Development Status :: 5 - Production/Stable
Classifier: Environment :: Console
Classifier: Environment :: Web Environment
Classifier: Framework :: Sphinx
Classifier: Framework :: Sphinx :: Extension
Classifier: Intended Audience :: Developers
Classifier: License :: OSI Approved :: MIT License
Classifier: Operating System :: OS Independent
Classifier: Programming Language :: Python
Classifier: Programming Language :: Python :: 3.10
Classifier: Programming Language :: Python :: 3.11
Classifier: Programming Language :: Python :: 3.12
Classifier: Programming Language :: Python :: 3.13
Classifier: Programming Language :: Python :: 3.14
Classifier: Topic :: Documentation
Classifier: Topic :: Documentation :: Sphinx
Classifier: Topic :: Software Development :: Libraries :: Python Modules
Classifier: Topic :: Utilities
Requires-Python: <4.0,>=3.10
Requires-Dist: sphinx>=6.0
Requires-Dist: typer-slim[standard]<1.0.0,>=0.12.0
Provides-Extra: html
Requires-Dist: selenium<5.0.0,>=4.0.0; extra == 'html'
Requires-Dist: webdriver-manager<5.0.0,>=3.0.0; extra == 'html'
Provides-Extra: pdf
Requires-Dist: cairosvg<3.0.0,>=2.7.0; extra == 'pdf'
Requires-Dist: lxml<7.0.0,>=4.2.0; extra == 'pdf'
Provides-Extra: png
Requires-Dist: pillow>=8.0.0; extra == 'png'
Requires-Dist: selenium<5.0.0,>=4.0.0; extra == 'png'
Requires-Dist: webdriver-manager<5.0.0,>=3.0.0; extra == 'png'
